angorapy/__init__.py
angorapy/evaluate.py
angorapy/pretrain.py
angorapy/train.py
angorapy/agent/__init__.py
angorapy/agent/dataio.py
angorapy/agent/gather.py
angorapy/agent/ppo_agent.py
angorapy/agent/utils.py
angorapy/agent/ppo/__init__.py
angorapy/agent/ppo/loss.py
angorapy/agent/ppo/optim.py
angorapy/agent/ppo/train_step.py
angorapy/analysis/__init__.py
angorapy/analysis/dynamics.py
angorapy/analysis/inspect_camera.py
angorapy/analysis/plot_future_translation_predictability.py
angorapy/analysis/plot_predictability.py
angorapy/analysis/plot_predictability_grouped.py
angorapy/analysis/plot_predictability_grouped_with_error_bars.py
angorapy/analysis/plot_predictability_with_error_bars.py
angorapy/analysis/plot_predictability_with_error_bars_single_figure.py
angorapy/analysis/plot_utils.py
angorapy/analysis/visualization.py
angorapy/analysis/investigators/__init__.py
angorapy/analysis/investigators/activity_autocorrelation.py
angorapy/analysis/investigators/base_investigator.py
angorapy/analysis/investigators/correlation.py
angorapy/analysis/investigators/dynamics.py
angorapy/analysis/investigators/predictability.py
angorapy/analysis/plotting/__init__.py
angorapy/analysis/plotting/autocorrelation_combined_plot.py
angorapy/analysis/plotting/make_viz_featuremax.py
angorapy/analysis/plotting/make_viz_pretraining_fmap.py
angorapy/analysis/plotting/make_viz_pretraining_saliency.py
angorapy/analysis/plotting/plot_benchmark.py
angorapy/analysis/plotting/plot_benchmark_groups.py
angorapy/analysis/plotting/plot_benchmark_groups_with_beta.py
angorapy/analysis/plotting/plot_distributed_computation_benchmark.py
angorapy/analysis/plotting/plot_experiment_best_evaluation.py
angorapy/analysis/plotting/plot_experiment_comparison.py
angorapy/analysis/plotting/plot_experiment_comparison_only_success_multiple_runs.py
angorapy/analysis/plotting/plot_experiment_comparison_only_success_multiple_runs_line_scatter.py
angorapy-0.10.8.dist-info/LICENSE
angorapy-0.10.8.dist-info/METADATA
angorapy-0.10.8.dist-info/WHEEL
angorapy-0.10.8.dist-info/top_level.txt
angorapy-0.10.8.dist-info/RECORD
