Metadata-Version: 2.1
Name: angorapy
Version: 0.10.8
Summary: Build Goal-driven Models of the Sensorimotor Cortex with Ease.
Home-page: http://www.angorapy.org
Author: Tonio Weidler
Author-email: research@tonioweidler.de
License: GPL-3.0
Classifier: Development Status :: 3 - Alpha
Classifier: Intended Audience :: Science/Research
Classifier: License :: OSI Approved :: GNU General Public License v3 (GPLv3)
Classifier: Operating System :: POSIX :: Linux
Classifier: Programming Language :: Python :: 3
Classifier: Programming Language :: Python :: 3.8
Classifier: Programming Language :: Python :: 3.9
Classifier: Programming Language :: Python :: 3.10
Requires-Python: >=3.8
License-File: LICENSE
Requires-Dist: imageio ==2.28.1
Requires-Dist: tensorflow[and-cuda] ==2.15.1
Requires-Dist: tensorflow-probability ==0.23.0
Requires-Dist: tensorflow-graphics ==2021.12.3
Requires-Dist: tensorflow-datasets
Requires-Dist: tqdm
Requires-Dist: simplejson
Requires-Dist: psutil
Requires-Dist: scipy
Requires-Dist: argcomplete
Requires-Dist: matplotlib
Requires-Dist: scikit-learn ==1.2.2
Requires-Dist: pandas ==1.4.4
Requires-Dist: nvidia-ml-py3
Requires-Dist: seaborn
Requires-Dist: distance
Requires-Dist: statsmodels ==0.14.0
Requires-Dist: keras-cortex ==0.0.8
Requires-Dist: mediapy
Requires-Dist: gymnasium[mujoco] ==0.28.1
Requires-Dist: mujoco
Requires-Dist: dm-control ==1.0.12
Requires-Dist: mujoco-utils
Provides-Extra: box2d
Requires-Dist: box2d-py ==2.3.5 ; extra == 'box2d'
Requires-Dist: gymnasium[box2d,mujoco] ==0.28.1 ; extra == 'box2d'
Provides-Extra: webinterface
Requires-Dist: itsdangerous ==2.0.1 ; extra == 'webinterface'
Requires-Dist: werkzeug ==2.0.3 ; extra == 'webinterface'
Requires-Dist: Flask ~=1.1.2 ; extra == 'webinterface'
Requires-Dist: Jinja2 ==3.0.3 ; extra == 'webinterface'
Requires-Dist: bokeh ==2.3.3 ; extra == 'webinterface'
Requires-Dist: flask-jsglue ; extra == 'webinterface'
